hugpy_module/__init__.py
hugpy_module/hugpy_module.py
hugpy_module/video_utils.py
hugpy_module/hugging_face_models/__init__.py
hugpy_module/hugging_face_models/config.py
hugpy_module/hugging_face_models/deepcoder.py
hugpy_module/hugging_face_models/google_flan.py
hugpy_module/hugging_face_models/keybert_model.py
hugpy_module/hugging_face_models/summarizer_model.py
hugpy_module/hugging_face_models/whisper_model.py
hugpy_module-0.0.0.1.dist-info/METADATA
hugpy_module-0.0.0.1.dist-info/WHEEL
hugpy_module-0.0.0.1.dist-info/top_level.txt
hugpy_module-0.0.0.1.dist-info/RECORD
